[
  {
    "id": 1,
    "grupo": "1-Bebidas calientes con café",
    "nombre": "Regular (Tamaño Unico)",
    "opcciona": "",
    "precio": "Unidad"
  },

  {
    "id": 2,
    "grupo": "2-Bebidas calientes con café",
    "nombre": "Regular (Tamaño Unico)",
    "opcciona": "",
    "precio": "Unidad"
  },
  {
    "id": 3,
    "grupo": "3-Bebidas calientes con café",
    "nombre": "Regular (Tamaño Unico)",
    "opcciona": "",
    "precio": "Unidad"
  },
  {
    "id": 4,
    "grupo": "3-Bebidas calientes con café",
    "nombre": "Regular (Tamaño Unico)",
    "opcciona": "",
    "precio": "Unidad"
  }
]
